[
    {
        "id": 1919545894,
        "user": "adriana.fdasg"
    },
    {
        "id": 52693975474,
        "user": "nsa_futsal"
    },
    {
        "id": 44584257508,
        "user": "staceyemilly"
    },
    {
        "id": 1181444732,
        "user": "alissondino00"
    },
    {
        "id": 56898177525,
        "user": "eduarda.fandr"
    },
    {
        "id": 532685979,
        "user": "isabelacambraiapita"
    },
    {
        "id": 26750593678,
        "user": "na.ny423"
    },
    {
        "id": 3212679361,
        "user": "annabeatriz.nc"
    },
    {
        "id": 44989429696,
        "user": "gislainy_santos4"
    },
    {
        "id": 68720187153,
        "user": "ancic4562024"
    },
    {
        "id": 1765870893,
        "user": "eduarda_afonsoo"
    },
    {
        "id": 10913819861,
        "user": "jlly_ssilvaa"
    },
    {
        "id": 57918850294,
        "user": "allves.wss"
    },
    {
        "id": 61714480590,
        "user": "maxz.vk"
    },
    {
        "id": 336733117,
        "user": "sergiogoncalvess__"
    },
    {
        "id": 58475212892,
        "user": "usuario2356_conta"
    },
    {
        "id": 59577892913,
        "user": "gislainearaujo_1"
    },
    {
        "id": 66169742434,
        "user": "_beatrizaraujo0_"
    },
    {
        "id": 60280364526,
        "user": "seguido817"
    },
    {
        "id": 60977398740,
        "user": "morena_fashion2023"
    },
    {
        "id": 37764861450,
        "user": "mirelladiasfernan_"
    },
    {
        "id": 47928835971,
        "user": "davidsantos7082"
    },
    {
        "id": 6093789772,
        "user": "sharasobral_avila"
    },
    {
        "id": 50347678435,
        "user": "mirellaraika24"
    },
    {
        "id": 667042750,
        "user": "sara_alenca"
    },
    {
        "id": 6364852608,
        "user": "rayssaevellen_"
    },
    {
        "id": 6036795582,
        "user": "avenidainformatica"
    },
    {
        "id": 3301444701,
        "user": "vanuza1623"
    },
    {
        "id": 47176100950,
        "user": "levifss_"
    },
    {
        "id": 534907842,
        "user": "lays_vitorias2"
    },
    {
        "id": 3186882347,
        "user": "joaoyune"
    },
    {
        "id": 1487733442,
        "user": "wagner_castro_maia"
    },
    {
        "id": 67572122628,
        "user": "blessed___321"
    },
    {
        "id": 11402756975,
        "user": "lohanyoliveiira"
    },
    {
        "id": 50577994688,
        "user": "deboraxaviiier"
    },
    {
        "id": 65128717199,
        "user": "p.vinni12"
    },
    {
        "id": 422812191,
        "user": "ivanlima12"
    },
    {
        "id": 5762838373,
        "user": "katiiasantos_"
    },
    {
        "id": 5362042139,
        "user": "fabricia3948"
    },
    {
        "id": 62512325791,
        "user": "m_vinni2005"
    },
    {
        "id": 6279934040,
        "user": "gislaine_pita"
    },
    {
        "id": 232730146,
        "user": "renan_fpinto"
    },
    {
        "id": 4288048561,
        "user": "isrrael_tavares"
    },
    {
        "id": 2187148414,
        "user": "teocfernandes"
    },
    {
        "id": 53577652522,
        "user": "alcidesluiz_"
    },
    {
        "id": 24304241001,
        "user": "urobsonsilva_"
    },
    {
        "id": 26947251328,
        "user": "jefersonrodrigues_90"
    },
    {
        "id": 26559960351,
        "user": "natanduarte71"
    },
    {
        "id": 1566623962,
        "user": "taysilvac"
    },
    {
        "id": 2253941367,
        "user": "dr.brenndonandrade"
    },
    {
        "id": 357662632,
        "user": "linear_engenhariaa"
    },
    {
        "id": 1371997263,
        "user": "pedro.lopes.71"
    },
    {
        "id": 504598860,
        "user": "dr.ivopita"
    },
    {
        "id": 428245281,
        "user": "andressamendoncaa"
    },
    {
        "id": 30559597756,
        "user": "ermesonslv_"
    },
    {
        "id": 422133570,
        "user": "karolcvieira"
    },
    {
        "id": 223780247,
        "user": "bibibraga2"
    },
    {
        "id": 1588988695,
        "user": "alexandre_salesfla"
    },
    {
        "id": 41184996548,
        "user": "josyhsampaio"
    },
    {
        "id": 2269569514,
        "user": "brendapalloma"
    },
    {
        "id": 6972651860,
        "user": "cinthialopesdos"
    },
    {
        "id": 2035460685,
        "user": "_mariaaevelyn"
    },
    {
        "id": 49927154489,
        "user": "gabie.dinizz"
    },
    {
        "id": 6822674194,
        "user": "luana_alvessantana"
    },
    {
        "id": 44203215517,
        "user": "luizafreitas_arq"
    },
    {
        "id": 4218282563,
        "user": "debora_joias"
    },
    {
        "id": 49545020278,
        "user": "leandrosousa212"
    },
    {
        "id": 10561614535,
        "user": "_narax011"
    },
    {
        "id": 4370421966,
        "user": "paulosilva2854"
    },
    {
        "id": 3627962671,
        "user": "telesmonike"
    },
    {
        "id": 11762246141,
        "user": "gledieg.arquiteto"
    },
    {
        "id": 263357623,
        "user": "isabelamenezesr"
    },
    {
        "id": 3195044410,
        "user": "karina_siilvaa"
    },
    {
        "id": 1430373760,
        "user": "jetterson_vieira"
    },
    {
        "id": 21965829510,
        "user": "leonardopaivasobreira"
    },
    {
        "id": 14247835753,
        "user": "jorio.ribeiro"
    },
    {
        "id": 15311215080,
        "user": "robertoalves.___"
    },
    {
        "id": 40537566047,
        "user": "rauazy"
    },
    {
        "id": 24356848466,
        "user": "_adjaa_p"
    },
    {
        "id": 2353451267,
        "user": "luciana_viidal"
    },
    {
        "id": 51866820349,
        "user": "celina_nasc11"
    },
    {
        "id": 46193160038,
        "user": "isaias_silvamr"
    },
    {
        "id": 1113639943,
        "user": "evilaniabarbosa14"
    },
    {
        "id": 5591498407,
        "user": "dry.bandeira"
    },
    {
        "id": 779924442,
        "user": "iigor.fig"
    },
    {
        "id": 41883940128,
        "user": "karolbellolemos"
    },
    {
        "id": 1534680422,
        "user": "alynebarrosss"
    },
    {
        "id": 52011517272,
        "user": "manelrlq.zy"
    },
    {
        "id": 52388246189,
        "user": "xsgloria__"
    },
    {
        "id": 25323588341,
        "user": "valeriatonho"
    },
    {
        "id": 64574991083,
        "user": "allisonema30"
    },
    {
        "id": 68183208689,
        "user": "_gabriel24463"
    },
    {
        "id": 2182575963,
        "user": "amanda.nobr"
    },
    {
        "id": 5468138142,
        "user": "pattrycia_crispim"
    },
    {
        "id": 429952486,
        "user": "luannajayza"
    },
    {
        "id": 3228337793,
        "user": "fabianematos.mendonca"
    },
    {
        "id": 8372569744,
        "user": "eliziane326"
    },
    {
        "id": 4458620357,
        "user": "matheus_registros"
    },
    {
        "id": 1947399005,
        "user": "alex.dasilvasantos.54"
    },
    {
        "id": 1305727700,
        "user": "jaquelinecv26"
    },
    {
        "id": 1155701768,
        "user": "emanuellasilva__"
    },
    {
        "id": 65783131207,
        "user": "rayanemendes22_29"
    },
    {
        "id": 53012455073,
        "user": "mari_sousa2334"
    },
    {
        "id": 314768016,
        "user": "karlabezerrag"
    },
    {
        "id": 43651211710,
        "user": "talydoliv"
    },
    {
        "id": 66973714506,
        "user": "mitcha_trajano"
    },
    {
        "id": 372066121,
        "user": "sarayorhana"
    },
    {
        "id": 65578917314,
        "user": "pricilla17oliveira"
    },
    {
        "id": 7219126704,
        "user": "allice__carlos"
    },
    {
        "id": 7987215606,
        "user": "ellen.matias.50"
    },
    {
        "id": 588403349,
        "user": "denisefelizardo"
    },
    {
        "id": 335601351,
        "user": "waleska_aquiino17"
    },
    {
        "id": 26077231393,
        "user": "enf.laislaianny"
    },
    {
        "id": 4173923735,
        "user": "nathaliadeise"
    },
    {
        "id": 21520721685,
        "user": "eduardo_soares.0.3"
    },
    {
        "id": 7326325384,
        "user": "mariaclara_palacio"
    },
    {
        "id": 846009079,
        "user": "marianacoosta_"
    },
    {
        "id": 62996937267,
        "user": "socorroalmeidab14"
    },
    {
        "id": 1488395377,
        "user": "cilios_emillypereira"
    },
    {
        "id": 52819065919,
        "user": "anacarolinabrito2003"
    },
    {
        "id": 62565139833,
        "user": "lucaasssoares19"
    },
    {
        "id": 65063008811,
        "user": "damianarib.eiro"
    },
    {
        "id": 7051341005,
        "user": "josymenezes4027"
    },
    {
        "id": 8239108326,
        "user": "audilene_biba"
    },
    {
        "id": 1555864649,
        "user": "eu_sampereira"
    },
    {
        "id": 66250301071,
        "user": "edyelliasantos"
    },
    {
        "id": 10591814459,
        "user": "souuvivi"
    },
    {
        "id": 25844606769,
        "user": "_liviasntt"
    },
    {
        "id": 9671382752,
        "user": "amandamello04"
    },
    {
        "id": 6798651894,
        "user": "telma_souza_as"
    },
    {
        "id": 1453700671,
        "user": "luanna_rocha18"
    },
    {
        "id": 184313378,
        "user": "janine.helder"
    },
    {
        "id": 371034523,
        "user": "siilmaralariissa"
    },
    {
        "id": 1742216885,
        "user": "anaherika_"
    },
    {
        "id": 4528674755,
        "user": "_mariia.sara"
    },
    {
        "id": 541505903,
        "user": "karol.1809"
    },
    {
        "id": 6710927201,
        "user": "edilania_e_ronaldo"
    },
    {
        "id": 28202925,
        "user": "claramorais.mv"
    },
    {
        "id": 59540604401,
        "user": "sarrania2513"
    },
    {
        "id": 8023591340,
        "user": "claaramacedoo"
    },
    {
        "id": 25028219766,
        "user": "angelaa_slv"
    },
    {
        "id": 46667858530,
        "user": "vanessa_p257"
    },
    {
        "id": 1527713849,
        "user": "kessia_kelly"
    },
    {
        "id": 5475123053,
        "user": "jessikabarbosa__"
    },
    {
        "id": 2337372154,
        "user": "dra.michelinedermatofuncional"
    },
    {
        "id": 50692044861,
        "user": "lojavirtual_daloma"
    },
    {
        "id": 44302490782,
        "user": "noelly_psi"
    },
    {
        "id": 2243919293,
        "user": "akizadantas"
    },
    {
        "id": 631535101,
        "user": "myllenasilva.of"
    },
    {
        "id": 66794419791,
        "user": "dagmapatriciataveiralima"
    },
    {
        "id": 3284203191,
        "user": "ana_souzaparente"
    },
    {
        "id": 2319403089,
        "user": "erica99lima"
    },
    {
        "id": 15534588184,
        "user": "angelaarraisadv"
    },
    {
        "id": 401326067,
        "user": "amandanails_p"
    },
    {
        "id": 1273601350,
        "user": "durcejanesantos"
    },
    {
        "id": 9060021198,
        "user": "edylaniarodrigues"
    },
    {
        "id": 8415820647,
        "user": "nataliapereira77"
    },
    {
        "id": 1182023303,
        "user": "claudiane9664"
    },
    {
        "id": 5459557344,
        "user": "vaninha3854"
    },
    {
        "id": 38527034390,
        "user": "kaldosekaldos"
    },
    {
        "id": 1433619416,
        "user": "simone_moura1985"
    },
    {
        "id": 6924109749,
        "user": "vamaquiando"
    },
    {
        "id": 6753939014,
        "user": "cristiane.leao.5264"
    },
    {
        "id": 18116564294,
        "user": "loveburgerfestival"
    },
    {
        "id": 659214487,
        "user": "leticiacrrd"
    },
    {
        "id": 65781273267,
        "user": "hewellinmelo"
    },
    {
        "id": 1963408789,
        "user": "tayana_oliveiraa"
    },
    {
        "id": 54535455929,
        "user": "lauraahoficial28"
    },
    {
        "id": 600373835,
        "user": "francismariaduarte"
    },
    {
        "id": 636509645,
        "user": "miirellakennedy"
    },
    {
        "id": 1140756089,
        "user": "eduardameloc"
    },
    {
        "id": 8554490194,
        "user": "helenamartins274"
    },
    {
        "id": 54013683599,
        "user": "rayllanny_11"
    },
    {
        "id": 3943910473,
        "user": "dewelly_sobreira"
    },
    {
        "id": 49040912751,
        "user": "beatriz.frr"
    },
    {
        "id": 52205195752,
        "user": "lucianarosa.rosa.9"
    },
    {
        "id": 313843123,
        "user": "hidayane"
    },
    {
        "id": 466082054,
        "user": "marquez_boutique_ce"
    },
    {
        "id": 593957698,
        "user": "bianca.wendiny"
    },
    {
        "id": 3956126990,
        "user": "_thayna2"
    },
    {
        "id": 262073781,
        "user": "joaopauloviana.adv"
    },
    {
        "id": 1945917711,
        "user": "gleycykellly"
    },
    {
        "id": 336018272,
        "user": "dra.izabellaalencar"
    },
    {
        "id": 3052072064,
        "user": "_mikaellybandeira"
    },
    {
        "id": 217931662,
        "user": "floragomes"
    },
    {
        "id": 1565738612,
        "user": "mari01_santos"
    },
    {
        "id": 8223339211,
        "user": "anacarolina.80"
    },
    {
        "id": 8093161324,
        "user": "marcia.pereira.98229"
    },
    {
        "id": 3439976332,
        "user": "mayara.2016"
    },
    {
        "id": 3462042343,
        "user": "cleideoliveiraa1"
    },
    {
        "id": 1424814154,
        "user": "oxkxo_lacerda"
    },
    {
        "id": 1149694343,
        "user": "brunaferreirajoao"
    },
    {
        "id": 1559953165,
        "user": "kelmateles"
    },
    {
        "id": 1352916357,
        "user": "ana_mariaalo"
    },
    {
        "id": 60013316465,
        "user": "daianetcf"
    },
    {
        "id": 7341647563,
        "user": "rafaellaconrrado"
    },
    {
        "id": 4568316135,
        "user": "eduardabritoxx"
    },
    {
        "id": 1305265432,
        "user": "thaynara.ofc"
    },
    {
        "id": 50598817415,
        "user": "josianealves1633"
    },
    {
        "id": 60088569615,
        "user": "alexaaa2601"
    },
    {
        "id": 463607815,
        "user": "miikatavares7"
    },
    {
        "id": 1152556149,
        "user": "monnyasobreira"
    },
    {
        "id": 50608616398,
        "user": "evilania35"
    },
    {
        "id": 3684167665,
        "user": "lucyamor_48"
    },
    {
        "id": 1205835729,
        "user": "anaynamendes"
    },
    {
        "id": 49990858217,
        "user": "nathalya.meloadv"
    },
    {
        "id": 1461490913,
        "user": "thaysinha.g"
    },
    {
        "id": 287934101,
        "user": "daniloecorrinha"
    },
    {
        "id": 25031119700,
        "user": "flav1nha_"
    },
    {
        "id": 7297335274,
        "user": "dannyelasantos_"
    },
    {
        "id": 57966120282,
        "user": "maria_paulaoliveiraa"
    },
    {
        "id": 8745246559,
        "user": "chikerestore"
    },
    {
        "id": 1396333270,
        "user": "bebellabratcho"
    },
    {
        "id": 49088695910,
        "user": "anna_jullia_52"
    },
    {
        "id": 312955210,
        "user": "allessandramartiins"
    },
    {
        "id": 44730595846,
        "user": "_mariaalencar_"
    },
    {
        "id": 8592935492,
        "user": "llu717950"
    },
    {
        "id": 489047583,
        "user": "fshlarissa"
    },
    {
        "id": 23207226497,
        "user": "luana_medeirosig"
    },
    {
        "id": 62225781393,
        "user": "faclubeday29"
    },
    {
        "id": 1519114091,
        "user": "lorenagrangeiro1"
    },
    {
        "id": 8538631167,
        "user": "larissagabryela27"
    },
    {
        "id": 37340572183,
        "user": "fran_goncalves_pereira"
    },
    {
        "id": 4290897995,
        "user": "gerlmsn"
    },
    {
        "id": 3890279592,
        "user": "eu_marasabrina342"
    },
    {
        "id": 59135294488,
        "user": "marcia_gabryella_"
    },
    {
        "id": 1370824430,
        "user": "ingridewlen"
    },
    {
        "id": 51819787033,
        "user": "aninhaviana2014"
    },
    {
        "id": 7445560493,
        "user": "resto_kaiana"
    },
    {
        "id": 62329738850,
        "user": "leonardo_fagundutra"
    },
    {
        "id": 57529615458,
        "user": "leonardo_josen"
    },
    {
        "id": 11081856549,
        "user": "_suelannysantos"
    },
    {
        "id": 413997238,
        "user": "talitaluannaa"
    },
    {
        "id": 48292457397,
        "user": "_p4ulohenriquebs"
    },
    {
        "id": 31507021938,
        "user": "ingrydhollanda"
    },
    {
        "id": 2151307894,
        "user": "yasminlivia"
    },
    {
        "id": 65814681363,
        "user": "marianxenofonte"
    },
    {
        "id": 593491079,
        "user": "erika_osouza"
    },
    {
        "id": 221051770,
        "user": "mayradantas.adv"
    },
    {
        "id": 502751216,
        "user": "dilamar_lopes"
    },
    {
        "id": 24009298712,
        "user": "glendamog"
    },
    {
        "id": 8460955485,
        "user": "naomiellen2002"
    },
    {
        "id": 7401199081,
        "user": "victoria.hyngrind"
    },
    {
        "id": 46138549372,
        "user": "elisabete.beta2021"
    },
    {
        "id": 62931736858,
        "user": "izabeldesignerdesobrancelhas"
    },
    {
        "id": 1255225331,
        "user": "yasmminfernandes_"
    },
    {
        "id": 2267577486,
        "user": "stefaniee_gomes"
    },
    {
        "id": 2217617185,
        "user": "naty_gui_valentina_maite"
    },
    {
        "id": 1647651368,
        "user": "crisliima_123"
    },
    {
        "id": 50121525838,
        "user": "nathalia.mdesantana"
    },
    {
        "id": 7467874451,
        "user": "floresdamagali_"
    },
    {
        "id": 1352500149,
        "user": "mm__vitoriaa_"
    },
    {
        "id": 35424796062,
        "user": "cheronliii"
    },
    {
        "id": 2098728768,
        "user": "alanakely59"
    },
    {
        "id": 2015677839,
        "user": "victoriianacleto"
    },
    {
        "id": 6692762165,
        "user": "brunamaia_1"
    },
    {
        "id": 549818749,
        "user": "jaionaram"
    },
    {
        "id": 1557299371,
        "user": "jeysinhadiasss"
    },
    {
        "id": 8241110121,
        "user": "_bethferreira__"
    },
    {
        "id": 2136970491,
        "user": "alicia_732"
    },
    {
        "id": 430913980,
        "user": "gleycesf"
    },
    {
        "id": 7686539196,
        "user": "cris_paulino7"
    },
    {
        "id": 4084528950,
        "user": "ronacys"
    },
    {
        "id": 272426140,
        "user": "jessicafbl"
    },
    {
        "id": 22560168883,
        "user": "021lucileny"
    },
    {
        "id": 20901540871,
        "user": "arlequinna_arlequinna"
    },
    {
        "id": 758184099,
        "user": "jhenifer_v"
    },
    {
        "id": 53002605674,
        "user": "adrieley_araujo_"
    },
    {
        "id": 2289327602,
        "user": "edivanyalima"
    },
    {
        "id": 1545767797,
        "user": "rosysousag"
    },
    {
        "id": 61554672885,
        "user": "hello_fsg"
    },
    {
        "id": 3267114909,
        "user": "laryssagbrito"
    },
    {
        "id": 51156087131,
        "user": "thais_fsineis"
    },
    {
        "id": 8223366246,
        "user": "rosangelaleiteoliveira"
    },
    {
        "id": 5328645857,
        "user": "sergilaniaferreira"
    },
    {
        "id": 10189274656,
        "user": "lari_bazilio1"
    },
    {
        "id": 5894085782,
        "user": "douglas.rudah"
    },
    {
        "id": 556887781,
        "user": "lorenamenesesm"
    },
    {
        "id": 5459505340,
        "user": "hiolanda_mariano"
    },
    {
        "id": 1318897541,
        "user": "wagner_goncalvees"
    },
    {
        "id": 5327548897,
        "user": "cicerageorgia"
    },
    {
        "id": 1561882969,
        "user": "dleyd_biquinis"
    },
    {
        "id": 60852988645,
        "user": "breno_souzzz"
    },
    {
        "id": 47805000350,
        "user": "marianasouza_tf"
    },
    {
        "id": 1967579977,
        "user": "anabiianca_"
    },
    {
        "id": 836462291,
        "user": "terezacalou"
    },
    {
        "id": 627142734,
        "user": "arniz_homem_e_mulher"
    },
    {
        "id": 1324551124,
        "user": "juceliatintino"
    },
    {
        "id": 26756569609,
        "user": "marciane2309"
    },
    {
        "id": 9714066853,
        "user": "espaco_smm_"
    },
    {
        "id": 6094299684,
        "user": "psi.julyanneduarte"
    },
    {
        "id": 1412027707,
        "user": "thamyrespetter"
    },
    {
        "id": 2270412194,
        "user": "jessicagama03"
    },
    {
        "id": 1286524435,
        "user": "daniela_freitas5623"
    },
    {
        "id": 59109145096,
        "user": "emanuelly_raykaa"
    },
    {
        "id": 40390021111,
        "user": "aamanda.barrros"
    },
    {
        "id": 7053322113,
        "user": "clarice_lima_esmalteria"
    },
    {
        "id": 51899161975,
        "user": "claramenezes750"
    },
    {
        "id": 3191342482,
        "user": "eujessikamatias__"
    },
    {
        "id": 1146136028,
        "user": "kessiagleycilene"
    },
    {
        "id": 53859274336,
        "user": "anabiatrizizidio"
    },
    {
        "id": 1433161003,
        "user": "rizaneidearaujo"
    },
    {
        "id": 1573576162,
        "user": "adeilda_sillva"
    },
    {
        "id": 37351893794,
        "user": "emili_goncalves1"
    },
    {
        "id": 1434881245,
        "user": "jessica_arroferia"
    },
    {
        "id": 7182513591,
        "user": "elidiane_marcarenhas"
    },
    {
        "id": 3782987712,
        "user": "_fernandaloppes"
    },
    {
        "id": 6496448050,
        "user": "helena_alana"
    },
    {
        "id": 58344773972,
        "user": "alinemascena3"
    },
    {
        "id": 44888799945,
        "user": "jaque___25"
    },
    {
        "id": 610722627,
        "user": "patriciaromaoo_"
    },
    {
        "id": 1532799919,
        "user": "israelliny"
    },
    {
        "id": 1785622926,
        "user": "ysa_candido"
    },
    {
        "id": 144575293,
        "user": "giannycosta"
    },
    {
        "id": 518541720,
        "user": "vickluana_"
    },
    {
        "id": 40435199563,
        "user": "karoo_laine"
    },
    {
        "id": 968771274,
        "user": "leticia_sza1"
    },
    {
        "id": 34806956966,
        "user": "vanessabeniciot"
    },
    {
        "id": 55921565702,
        "user": "pam.melk88"
    },
    {
        "id": 1669160148,
        "user": "yasmim.ol19"
    },
    {
        "id": 252152202,
        "user": "raquelfreoliv"
    },
    {
        "id": 475736437,
        "user": "cleitianedamasceno"
    },
    {
        "id": 58341702422,
        "user": "ivanniacardoso"
    },
    {
        "id": 209336685,
        "user": "maria_helena2207"
    },
    {
        "id": 1334739537,
        "user": "wiviannytavares"
    },
    {
        "id": 583395029,
        "user": "vytoria_delma"
    },
    {
        "id": 37057767461,
        "user": "tamiresleitee_"
    },
    {
        "id": 6577144085,
        "user": "_hyngridy"
    },
    {
        "id": 26693880,
        "user": "draemanuellycouras"
    },
    {
        "id": 60697536241,
        "user": "thicianyn"
    },
    {
        "id": 50469689264,
        "user": "ab_nadie"
    },
    {
        "id": 440808943,
        "user": "nathanarrais"
    },
    {
        "id": 2710474013,
        "user": "edvania_leandro"
    },
    {
        "id": 44848614214,
        "user": "layanny_torres"
    },
    {
        "id": 47836074146,
        "user": "jaynara_rodriguess_"
    },
    {
        "id": 26294622536,
        "user": "jhessikvaniell"
    },
    {
        "id": 4076304127,
        "user": "larissa.irony"
    },
    {
        "id": 3280656744,
        "user": "_joannalr"
    },
    {
        "id": 12825224158,
        "user": "heloisa_eufrsio"
    },
    {
        "id": 61874979866,
        "user": "ozenelenobrecruzduarte"
    },
    {
        "id": 27170705477,
        "user": "edna_karla_lima"
    },
    {
        "id": 2322694168,
        "user": "enf_nathalyasillva"
    },
    {
        "id": 2318875421,
        "user": "larissa.carvalhogf"
    },
    {
        "id": 35175913859,
        "user": "vic.toriamunizd"
    },
    {
        "id": 65190800069,
        "user": "estetica_annaluiza"
    },
    {
        "id": 8175904076,
        "user": "arraistammy"
    },
    {
        "id": 1389795213,
        "user": "giuliannevasconcelos"
    },
    {
        "id": 5832934770,
        "user": "giselly_lacerdaa"
    },
    {
        "id": 48583978661,
        "user": "grazycavalcante20"
    },
    {
        "id": 283579634,
        "user": "brunomacedoadv"
    },
    {
        "id": 66625824453,
        "user": "jnpublicbrasil.24"
    },
    {
        "id": 504496128,
        "user": "samira_ap_costa"
    },
    {
        "id": 4635829452,
        "user": "duda__bernardinelli"
    },
    {
        "id": 1602918380,
        "user": "jessicapradoflor"
    },
    {
        "id": 28514722264,
        "user": "ismael_sillva_"
    },
    {
        "id": 33126663676,
        "user": "cesaralves_am"
    },
    {
        "id": 6874697006,
        "user": "aparecidaoliveiraofc"
    },
    {
        "id": 522436776,
        "user": "euuhellenx"
    },
    {
        "id": 182406947,
        "user": "elisrayane"
    },
    {
        "id": 46287233170,
        "user": "edigessoqc"
    },
    {
        "id": 4404980252,
        "user": "martasabrina_"
    },
    {
        "id": 17076224293,
        "user": "izadora_gal"
    },
    {
        "id": 3682059998,
        "user": "ana.p._"
    },
    {
        "id": 1366612948,
        "user": "williamvieira008"
    },
    {
        "id": 66290992318,
        "user": "vendedor_juazeirodo"
    },
    {
        "id": 66312066119,
        "user": "karoljeronimo33"
    },
    {
        "id": 429475095,
        "user": "ellisraynaoli_"
    },
    {
        "id": 7513106612,
        "user": "sergiosolsa"
    },
    {
        "id": 7040560278,
        "user": "_marianacostadn"
    },
    {
        "id": 8197712816,
        "user": "millyy_ly"
    },
    {
        "id": 56791761288,
        "user": "liacastro_07"
    },
    {
        "id": 2696923702,
        "user": "ana_luisa1400"
    },
    {
        "id": 56905300843,
        "user": "jucia_naa"
    },
    {
        "id": 5319260038,
        "user": "_nayarahellen"
    },
    {
        "id": 549777857,
        "user": "vitorinoedu"
    },
    {
        "id": 1959521333,
        "user": "ediane.mariah"
    },
    {
        "id": 45974635495,
        "user": "mellodyerika"
    },
    {
        "id": 1967547696,
        "user": "kethylingiovana"
    },
    {
        "id": 39022085655,
        "user": "daniziodejesus"
    },
    {
        "id": 18729181208,
        "user": "_anna_souza09"
    },
    {
        "id": 44984576462,
        "user": "_larxsss_"
    },
    {
        "id": 52416738545,
        "user": "naiarasva"
    },
    {
        "id": 11634142134,
        "user": "jocasta_aalmeida"
    },
    {
        "id": 1547188240,
        "user": "ellisamorim"
    },
    {
        "id": 48648139280,
        "user": "micaelly0812"
    },
    {
        "id": 15679631922,
        "user": "vitoria.fernanndes"
    },
    {
        "id": 61214845043,
        "user": "jay.karlla"
    },
    {
        "id": 64739160460,
        "user": "gremioneoalpha"
    },
    {
        "id": 62456488886,
        "user": "abelardooo6271"
    },
    {
        "id": 47966410719,
        "user": "m.joao.v.r.1224.eu"
    },
    {
        "id": 62799575730,
        "user": "gustavo210333"
    },
    {
        "id": 55028653593,
        "user": "_viih_souza2102"
    },
    {
        "id": 58227208159,
        "user": "marxz.dzh22"
    },
    {
        "id": 59497403212,
        "user": "jamirle123"
    },
    {
        "id": 54882883829,
        "user": "rikelme_mineiro1"
    },
    {
        "id": 65654837593,
        "user": "romildo5112"
    },
    {
        "id": 1523344967,
        "user": "rosyxenofonte"
    },
    {
        "id": 60721736615,
        "user": "_pedrinho__dl"
    },
    {
        "id": 2300904507,
        "user": "suelenmaede2casal"
    },
    {
        "id": 61936176781,
        "user": "geneson_05ofc"
    },
    {
        "id": 58588177844,
        "user": "clarinha28799"
    },
    {
        "id": 10681655431,
        "user": "eunice210334"
    },
    {
        "id": 43686327747,
        "user": "eu.meire_r"
    },
    {
        "id": 58135991453,
        "user": "jona_tas264"
    },
    {
        "id": 521314987,
        "user": "naah_silva09"
    },
    {
        "id": 62605293668,
        "user": "sarah_yasmin_._77"
    },
    {
        "id": 62436822048,
        "user": "deboranascimento_oliveira"
    },
    {
        "id": 66322389427,
        "user": "jesicassilvasilva11"
    },
    {
        "id": 64042437081,
        "user": "lica.vic"
    },
    {
        "id": 63764305334,
        "user": "_marihh.y_"
    },
    {
        "id": 2318071329,
        "user": "sm_souzaaa"
    },
    {
        "id": 58762583379,
        "user": "joaoxz.__7"
    },
    {
        "id": 58038186723,
        "user": "morena.jay54"
    },
    {
        "id": 33753166706,
        "user": "kauan_petter011"
    },
    {
        "id": 62970526684,
        "user": "kenn.edy9138"
    },
    {
        "id": 64285665482,
        "user": "sophiakauni7"
    },
    {
        "id": 60315195424,
        "user": "lcszin_v7"
    },
    {
        "id": 56293172576,
        "user": "leo_10_pdm"
    },
    {
        "id": 57144495555,
        "user": "anax.2105"
    },
    {
        "id": 33551591041,
        "user": "abreuudiass__"
    },
    {
        "id": 61863100582,
        "user": "jamyss8"
    },
    {
        "id": 7041669354,
        "user": "deborahhbbarros"
    },
    {
        "id": 65627734293,
        "user": "cristinas_anjo"
    },
    {
        "id": 22391329417,
        "user": "patriciasilva1882"
    },
    {
        "id": 6761637250,
        "user": "aclaudiareginade"
    },
    {
        "id": 59642433858,
        "user": "__fernandes_kz_"
    },
    {
        "id": 59612227615,
        "user": "silv.cacau"
    },
    {
        "id": 1772405861,
        "user": "taisssiqueira"
    },
    {
        "id": 49970029079,
        "user": "ritadecassialobatoda"
    },
    {
        "id": 64670213552,
        "user": "kailane3518"
    },
    {
        "id": 2078452117,
        "user": "ed.inacio463"
    },
    {
        "id": 57236906972,
        "user": "isaa24k___"
    },
    {
        "id": 57992099432,
        "user": "moniquinha_abencoada"
    },
    {
        "id": 11041697325,
        "user": "camile.cavalcanti"
    },
    {
        "id": 54301067587,
        "user": "otthais"
    },
    {
        "id": 58604107193,
        "user": "conta_resevar1"
    },
    {
        "id": 8088873655,
        "user": "_iaraalmeiida"
    },
    {
        "id": 44965577339,
        "user": "ju_martins017"
    },
    {
        "id": 14522133975,
        "user": "vini_santos24242424"
    },
    {
        "id": 58806447619,
        "user": "angellyna118"
    },
    {
        "id": 27155964808,
        "user": "_manuzinha1235"
    },
    {
        "id": 51519796348,
        "user": "eupedroarthu_ofc"
    },
    {
        "id": 58736158895,
        "user": "dyasmikele"
    },
    {
        "id": 58353469208,
        "user": "pret.arrara33"
    },
    {
        "id": 17188953186,
        "user": "maary_liimaa"
    },
    {
        "id": 63923091073,
        "user": "_matheus.medeiross"
    },
    {
        "id": 61231505937,
        "user": "vlog_da_barbie_1"
    },
    {
        "id": 11538405515,
        "user": "andreia_unhas_belas"
    },
    {
        "id": 52130358244,
        "user": "biatrzzr"
    },
    {
        "id": 59107774161,
        "user": "_vixii_nicolly_67"
    },
    {
        "id": 762912519,
        "user": "zenyr.orozco"
    },
    {
        "id": 11624030499,
        "user": "patriciaoliveiramanu"
    },
    {
        "id": 29084783212,
        "user": "kaah_franca3736"
    },
    {
        "id": 64157724493,
        "user": "jjxtrem_015"
    },
    {
        "id": 7100856633,
        "user": "willilove80"
    },
    {
        "id": 61012272355,
        "user": "gica_bateradrum"
    },
    {
        "id": 51706271567,
        "user": "_roque1807"
    },
    {
        "id": 1181351656,
        "user": "pamella_santos_135"
    },
    {
        "id": 23210653139,
        "user": "kethelencaroline10_"
    },
    {
        "id": 29906321315,
        "user": "amanda_ellen052"
    },
    {
        "id": 25733043235,
        "user": "edienekauaketleymarcia"
    },
    {
        "id": 64423934847,
        "user": "jessica6752024"
    },
    {
        "id": 54901682190,
        "user": "ana_fabia_silva"
    },
    {
        "id": 60277296539,
        "user": "familia.na.fe"
    },
    {
        "id": 7148154857,
        "user": "wellington2024alves"
    },
    {
        "id": 45852773052,
        "user": "caahvariedades"
    },
    {
        "id": 60169903213,
        "user": "solzinho919"
    },
    {
        "id": 58222132530,
        "user": "4fami.lia"
    },
    {
        "id": 66246351344,
        "user": "33_matheus_244"
    },
    {
        "id": 61005977639,
        "user": "jerff29"
    },
    {
        "id": 66530705013,
        "user": "pvd__guguhh"
    },
    {
        "id": 64256241144,
        "user": "leo_73727"
    },
    {
        "id": 60792118524,
        "user": "gideone9941"
    },
    {
        "id": 46267390974,
        "user": "licynhahh_souzahh"
    },
    {
        "id": 61880546117,
        "user": "iae_ryanzs012"
    },
    {
        "id": 55301797314,
        "user": "isahxx99"
    },
    {
        "id": 66337725236,
        "user": "emily_seraphimm"
    },
    {
        "id": 39266068006,
        "user": "sheilaerickph"
    },
    {
        "id": 43813373382,
        "user": "flaviane4924"
    },
    {
        "id": 60637942319,
        "user": "sofia21033"
    },
    {
        "id": 51147387320,
        "user": "kauanzinho302"
    },
    {
        "id": 47450040886,
        "user": "problematicademell"
    },
    {
        "id": 38303166513,
        "user": "muriloclara438"
    },
    {
        "id": 66521364273,
        "user": "lets78k"
    },
    {
        "id": 28867273323,
        "user": "smith.tjb_"
    },
    {
        "id": 62309596951,
        "user": "_244_ofc_.para_"
    },
    {
        "id": 53150918723,
        "user": "gabrielx7adm"
    },
    {
        "id": 36289590242,
        "user": "josemariamouradesousa"
    },
    {
        "id": 45619630920,
        "user": "mariih_bastoss35"
    },
    {
        "id": 58602265286,
        "user": "5.guiii"
    },
    {
        "id": 24673008996,
        "user": "laudenicec9"
    },
    {
        "id": 5921659159,
        "user": "samantha_samuelzinho"
    },
    {
        "id": 61364516846,
        "user": "rodrigues654_4"
    },
    {
        "id": 60172111554,
        "user": "vitorportella2023"
    },
    {
        "id": 60148389275,
        "user": "vilmam249"
    },
    {
        "id": 61856379283,
        "user": "vanessaq_q"
    },
    {
        "id": 61441250840,
        "user": "romulo_o632"
    },
    {
        "id": 61935623078,
        "user": "romarioo170"
    },
    {
        "id": 61622556125,
        "user": "raq.uel4819"
    },
    {
        "id": 58859191927,
        "user": "rosa.dosdias"
    },
    {
        "id": 61749127907,
        "user": "naoomii458"
    },
    {
        "id": 60166404702,
        "user": "gregoryribamar_4"
    },
    {
        "id": 60622858925,
        "user": "charlotte.37733"
    },
    {
        "id": 63003103815,
        "user": "xavieer902"
    },
    {
        "id": 61168097959,
        "user": "thiagoo4735"
    },
    {
        "id": 61863741715,
        "user": "marcioo51"
    },
    {
        "id": 61794708367,
        "user": "margaridafranciscaa3"
    },
    {
        "id": 63856388314,
        "user": "paulo00op"
    },
    {
        "id": 64171824108,
        "user": "paoloogui"
    },
    {
        "id": 62418357444,
        "user": "patriiciaa54"
    },
    {
        "id": 61984920542,
        "user": "pamelaf7263"
    },
    {
        "id": 61961914788,
        "user": "marquinhoss883"
    },
    {
        "id": 61855700147,
        "user": "marcia.as69"
    },
    {
        "id": 61413520959,
        "user": "lima_9970"
    },
    {
        "id": 63007381086,
        "user": "lorrainee819"
    },
    {
        "id": 60867221301,
        "user": "ferdinanda5867"
    },
    {
        "id": 61809119286,
        "user": "claudia16727"
    },
    {
        "id": 60903425318,
        "user": "fluxo.almeida78"
    },
    {
        "id": 60892210929,
        "user": "ferreiraa_1996"
    },
    {
        "id": 61748285438,
        "user": "felipee.202"
    },
    {
        "id": 61720444476,
        "user": "britto36_6"
    },
    {
        "id": 60889051183,
        "user": "barradas_58.michelle"
    },
    {
        "id": 56887742343,
        "user": "lima.re35"
    },
    {
        "id": 53895819646,
        "user": "escutaoruyter"
    },
    {
        "id": 62139335143,
        "user": "mariaa6jj"
    },
    {
        "id": 47248879642,
        "user": "ramos_amorim99"
    },
    {
        "id": 57510033417,
        "user": "princesinhak2"
    },
    {
        "id": 65812875769,
        "user": "gabyy29l"
    },
    {
        "id": 62909063912,
        "user": "allamo07"
    },
    {
        "id": 54528064428,
        "user": "enzoxs._.daspty777"
    },
    {
        "id": 64293636033,
        "user": "aguiat277"
    },
    {
        "id": 62654993968,
        "user": "branquinho_.444"
    },
    {
        "id": 8374365450,
        "user": "rodrigue_ll"
    },
    {
        "id": 61374179363,
        "user": "drx_mh_trem_021"
    },
    {
        "id": 50286819937,
        "user": "jv_do_digital6"
    },
    {
        "id": 57017233596,
        "user": "dayani_siilva"
    },
    {
        "id": 47706456331,
        "user": "diogomarquesreserva79"
    },
    {
        "id": 64803720353,
        "user": "__marcio_silva_04"
    },
    {
        "id": 61247169992,
        "user": "rst.tatazinha"
    },
    {
        "id": 46885528341,
        "user": "alme.idaa9"
    },
    {
        "id": 61117547519,
        "user": "anax_alicekkk"
    },
    {
        "id": 48983537615,
        "user": "karina_ribeiro_091m"
    },
    {
        "id": 2006002816,
        "user": "camila_.s5"
    },
    {
        "id": 65090698524,
        "user": "memes_coreano_244_free_fire"
    },
    {
        "id": 60961882978,
        "user": "_biaxx081"
    },
    {
        "id": 62857148456,
        "user": "vitinrjkk_"
    },
    {
        "id": 66496201932,
        "user": "reservadadigatta"
    },
    {
        "id": 58752783938,
        "user": "s.hanini.v.c"
    },
    {
        "id": 61796988157,
        "user": "m1234ig"
    },
    {
        "id": 49649500757,
        "user": "yansenna9891"
    },
    {
        "id": 64200368602,
        "user": "anegabriellycastrode"
    },
    {
        "id": 61114408953,
        "user": "elaine_e969"
    },
    {
        "id": 58504301377,
        "user": "agatha_acris7"
    },
    {
        "id": 58904715936,
        "user": "8726bih"
    },
    {
        "id": 60680012349,
        "user": "jessy1.06"
    },
    {
        "id": 54663923221,
        "user": "bebezinha21c"
    },
    {
        "id": 1932930853,
        "user": "stanley_estevao_02"
    },
    {
        "id": 64228544092,
        "user": "fhugo9"
    },
    {
        "id": 1481557737,
        "user": "_jessilimaa"
    },
    {
        "id": 3090529159,
        "user": "cassia2066"
    },
    {
        "id": 4142930500,
        "user": "carleane_alencar"
    },
    {
        "id": 5395554963,
        "user": "jose_ewertoncosta"
    },
    {
        "id": 1420999405,
        "user": "rebeca_alencar17"
    },
    {
        "id": 510600390,
        "user": "_andressasalles"
    },
    {
        "id": 56848984413,
        "user": "frjoanderson"
    },
    {
        "id": 42503676888,
        "user": "nopontodosmagnatas"
    },
    {
        "id": 26898031144,
        "user": "rafaagmz_"
    },
    {
        "id": 65912822390,
        "user": "luaa_juuh1"
    },
    {
        "id": 62960764163,
        "user": "isaa.n3k"
    },
    {
        "id": 65046549747,
        "user": "vivi.silva96l"
    },
    {
        "id": 46287752394,
        "user": "souk67.s"
    },
    {
        "id": 45461847055,
        "user": "_jucyy_00"
    },
    {
        "id": 55272551386,
        "user": "mirlane489"
    },
    {
        "id": 65938537752,
        "user": "maguinhah620"
    },
    {
        "id": 62568600163,
        "user": "andr.ade9780"
    },
    {
        "id": 66313297471,
        "user": "marci.alves530"
    },
    {
        "id": 44903109486,
        "user": "jhom_slots"
    },
    {
        "id": 49523964827,
        "user": "vanderleiadacruzsoares"
    },
    {
        "id": 66379779063,
        "user": "karinamarquez432"
    },
    {
        "id": 45372925935,
        "user": "giiihsousa2"
    },
    {
        "id": 65161262026,
        "user": "jonathan10_46"
    },
    {
        "id": 46481393271,
        "user": "milena__183"
    },
    {
        "id": 66260728907,
        "user": "alves100__"
    },
    {
        "id": 30074923041,
        "user": "mariii_628"
    },
    {
        "id": 49420177692,
        "user": "maria_morais1512"
    },
    {
        "id": 44493556843,
        "user": "eu.rosilaine"
    },
    {
        "id": 50646748281,
        "user": "escobarjp074"
    },
    {
        "id": 3076520155,
        "user": "brunaa_cibelee"
    },
    {
        "id": 6350788666,
        "user": "kathleen_0y0"
    },
    {
        "id": 3425155018,
        "user": "franciellysilva0719"
    },
    {
        "id": 56939147812,
        "user": "mary_vitoria867"
    },
    {
        "id": 49815672206,
        "user": "meno_rdk_021"
    },
    {
        "id": 62943904982,
        "user": "massoterapeutamarcoslima"
    },
    {
        "id": 52190480988,
        "user": "micheliana_andrade"
    },
    {
        "id": 45677833609,
        "user": "vanna.mello05"
    },
    {
        "id": 22683113953,
        "user": "diinha_viiana"
    },
    {
        "id": 63896581470,
        "user": "paes.wv"
    },
    {
        "id": 10087965722,
        "user": "jenifersoares234"
    },
    {
        "id": 54729590527,
        "user": "_luandersantos"
    },
    {
        "id": 11610790752,
        "user": "lorraine_realli"
    },
    {
        "id": 9070061415,
        "user": "marmitaria_buffet.rodrigues"
    },
    {
        "id": 3697418225,
        "user": "maria.aparecida3362"
    },
    {
        "id": 10428678187,
        "user": "rosilene8562"
    },
    {
        "id": 5862933345,
        "user": "brunna__sssouza"
    },
    {
        "id": 7719375209,
        "user": "gleicyanemarreiros"
    },
    {
        "id": 54051255212,
        "user": "f_a_n_t_a_s_m_i_n_h_a_1_6"
    },
    {
        "id": 62774547512,
        "user": "cianagomes50"
    },
    {
        "id": 38585125217,
        "user": "mayara_a2020"
    },
    {
        "id": 6732137194,
        "user": "andrezalima521"
    },
    {
        "id": 66490201422,
        "user": "leticiabarrettoss"
    },
    {
        "id": 65076495628,
        "user": "zete_fenix"
    },
    {
        "id": 12124814159,
        "user": "bellaemarysantos"
    },
    {
        "id": 53690232631,
        "user": "gato_galacticoo"
    },
    {
        "id": 56030784437,
        "user": "fraciane_b"
    },
    {
        "id": 4226088912,
        "user": "cinthianathyelly"
    },
    {
        "id": 62800328178,
        "user": "pvd_mariosamuel"
    },
    {
        "id": 7213638431,
        "user": "josykelly9893"
    },
    {
        "id": 65451764928,
        "user": "4m.pereiraw"
    },
    {
        "id": 60890550567,
        "user": "_doisl_55"
    },
    {
        "id": 64049536451,
        "user": "la.rissa9983"
    },
    {
        "id": 60642405384,
        "user": "vitoriaregina236"
    },
    {
        "id": 58892645641,
        "user": "vitoriareginados4"
    },
    {
        "id": 66322623544,
        "user": "cherry_beauty_cosmeticos"
    },
    {
        "id": 53352183400,
        "user": "k7_animes"
    },
    {
        "id": 7258678401,
        "user": "flaviane.paixao"
    },
    {
        "id": 64140707480,
        "user": "anthonx.zzhh11"
    },
    {
        "id": 53721321967,
        "user": "mlk.sonhador40"
    },
    {
        "id": 66335903250,
        "user": "brun.asilva4459"
    },
    {
        "id": 48535872181,
        "user": "silvapollyana97473"
    },
    {
        "id": 63880363026,
        "user": "almeidaxr11"
    },
    {
        "id": 56098750223,
        "user": "lc_zx_silvax"
    },
    {
        "id": 46008015800,
        "user": "carol.batalha.92"
    },
    {
        "id": 50374437912,
        "user": "vida.me.surpreendaaaa"
    },
    {
        "id": 65969727818,
        "user": "eaii_.larah"
    },
    {
        "id": 58758814193,
        "user": "eubiasinha15"
    },
    {
        "id": 1966350881,
        "user": "alana_pinheiro"
    },
    {
        "id": 61240985820,
        "user": "robertaalves6479"
    },
    {
        "id": 62350342664,
        "user": "silva.dllx"
    },
    {
        "id": 66366298119,
        "user": "sos82934"
    },
    {
        "id": 1202433921,
        "user": "barbarafalves13"
    },
    {
        "id": 49948779860,
        "user": "eai.rosi_s"
    },
    {
        "id": 51648542114,
        "user": "kaua_morais155"
    },
    {
        "id": 51792309097,
        "user": "thaai_90"
    },
    {
        "id": 52256948531,
        "user": "anasousa1690"
    },
    {
        "id": 61287065065,
        "user": "eu_maryannasilva_"
    },
    {
        "id": 66361274762,
        "user": "siivzz_44"
    },
    {
        "id": 49890286410,
        "user": "felipe_cria_01"
    },
    {
        "id": 54289621478,
        "user": "kawannewill_"
    },
    {
        "id": 44035699730,
        "user": "duda_wa_062"
    },
    {
        "id": 65575655020,
        "user": "vivi_kirida_11"
    },
    {
        "id": 62660773182,
        "user": "hadassasophia30"
    },
    {
        "id": 64364080143,
        "user": "gabriela.xps7"
    },
    {
        "id": 44177375342,
        "user": "eu.r_s"
    },
    {
        "id": 66389056963,
        "user": "mah.cacheada24"
    },
    {
        "id": 22227499393,
        "user": "valeria.dossantos.35912672"
    },
    {
        "id": 54634671909,
        "user": "theo_lucchesi10"
    },
    {
        "id": 59415687190,
        "user": "luax9529"
    },
    {
        "id": 55657105438,
        "user": "oxii_ias_min_000"
    },
    {
        "id": 54758871623,
        "user": "013_bielzinho09"
    },
    {
        "id": 64222480415,
        "user": "biianca.024_"
    },
    {
        "id": 54906266697,
        "user": "yarah_santtos_"
    },
    {
        "id": 62330470873,
        "user": "aaa._tata"
    },
    {
        "id": 51298070230,
        "user": "hz_leonardo_21"
    },
    {
        "id": 62739667494,
        "user": "_duqueza_de_la_furia"
    },
    {
        "id": 65939906325,
        "user": "josiel_dograu_244"
    },
    {
        "id": 62808453774,
        "user": "sub.platz"
    },
    {
        "id": 61548083427,
        "user": "jaislane64"
    },
    {
        "id": 60034844474,
        "user": "samuca__piloto46"
    },
    {
        "id": 65246485700,
        "user": "yaramiranda547"
    },
    {
        "id": 66723036426,
        "user": "rlkda_niel07"
    },
    {
        "id": 62143409506,
        "user": "yzin.2k24"
    },
    {
        "id": 3289676235,
        "user": "marinelimeyer"
    },
    {
        "id": 5660055177,
        "user": "alltshirts.oficial"
    },
    {
        "id": 1527784239,
        "user": "beatrizfreire21"
    },
    {
        "id": 17928949602,
        "user": "mariasocorropd"
    },
    {
        "id": 62132835470,
        "user": "ana_prycyla_privad"
    },
    {
        "id": 26710978636,
        "user": "isabellaangeloas"
    },
    {
        "id": 2161633836,
        "user": "tamylisfonseca"
    },
    {
        "id": 47453932599,
        "user": "francislene_arrais"
    },
    {
        "id": 642104937,
        "user": "eugenia_davinc"
    },
    {
        "id": 415188227,
        "user": "drafernaandacf"
    },
    {
        "id": 21705691260,
        "user": "rlima_empreendimentos"
    },
    {
        "id": 1097552992,
        "user": "ricardolima_79"
    },
    {
        "id": 34505897438,
        "user": "daily.lelecr2_"
    },
    {
        "id": 48258973634,
        "user": "givanilda.ferreira.90260"
    },
    {
        "id": 64747896437,
        "user": "beatriz24327"
    },
    {
        "id": 59362538361,
        "user": "_nicollyzzx5_"
    },
    {
        "id": 61862491606,
        "user": "duda_santos2o"
    },
    {
        "id": 62570495533,
        "user": "regina_oliveira_72"
    },
    {
        "id": 50309746332,
        "user": "hariely_trancas"
    },
    {
        "id": 58248166175,
        "user": "nenem_gabriel037"
    },
    {
        "id": 25034641765,
        "user": "talles17_08"
    },
    {
        "id": 48214257405,
        "user": "eugaelalerrandro"
    },
    {
        "id": 64756284777,
        "user": "ketma1234"
    },
    {
        "id": 40648458632,
        "user": "andreza_bgm09"
    },
    {
        "id": 48809001488,
        "user": "rafeela.santos09"
    },
    {
        "id": 61343775719,
        "user": "souzzsx.10"
    },
    {
        "id": 39173342918,
        "user": "jessicacarvalho848"
    },
    {
        "id": 26455852223,
        "user": "_bonus_free"
    },
    {
        "id": 31742957708,
        "user": "leidislaynne"
    },
    {
        "id": 1001581534,
        "user": "jotobal"
    },
    {
        "id": 7598753280,
        "user": "zenaide_albuquerquee"
    },
    {
        "id": 409681042,
        "user": "shyldlima"
    },
    {
        "id": 65140047585,
        "user": "tatianepocah"
    },
    {
        "id": 19757169800,
        "user": "jessica.nlima"
    },
    {
        "id": 2076138896,
        "user": "dhiessika_martins"
    },
    {
        "id": 48504022193,
        "user": "wanessarocha18"
    },
    {
        "id": 52946737822,
        "user": "dudasouza20000"
    },
    {
        "id": 12054660589,
        "user": "sales.luiz.luciano"
    },
    {
        "id": 43701066581,
        "user": "rodrigues___2008"
    },
    {
        "id": 44839025746,
        "user": "dyemelesouza"
    },
    {
        "id": 5400791750,
        "user": "silvaneide_pontes_de_franca_5"
    },
    {
        "id": 64606446280,
        "user": "thaemyli56"
    },
    {
        "id": 34246700734,
        "user": "chefinho_das_platarmas"
    },
    {
        "id": 48030233970,
        "user": "julianemaiadesigner"
    },
    {
        "id": 28642052881,
        "user": "jak_jales"
    },
    {
        "id": 59043064356,
        "user": "yohandrimarquez92023"
    },
    {
        "id": 62278946948,
        "user": "duda_maria_ixiii244"
    },
    {
        "id": 2315394841,
        "user": "marta4480"
    },
    {
        "id": 17197335563,
        "user": "aninha__gom"
    },
    {
        "id": 62101361002,
        "user": "renanjbl10"
    },
    {
        "id": 5538183892,
        "user": "ednamendes4937"
    },
    {
        "id": 32032649731,
        "user": "lleo_zim"
    },
    {
        "id": 10716381779,
        "user": "brunadasilvacrispiniane"
    },
    {
        "id": 59340279343,
        "user": "akylla251"
    },
    {
        "id": 61633650280,
        "user": "lk_henrique_gabriel"
    },
    {
        "id": 25263037793,
        "user": "ari_santos.moreninha"
    },
    {
        "id": 1170549524,
        "user": "josiane__motta"
    },
    {
        "id": 26757384796,
        "user": "elainecosta28_"
    },
    {
        "id": 36894854923,
        "user": "kelly.fernandes426"
    },
    {
        "id": 2226728908,
        "user": "kacyh_amorim24"
    },
    {
        "id": 7613821759,
        "user": "enf_evelin.carvalho"
    },
    {
        "id": 13690537267,
        "user": "luiz_fernando064"
    },
    {
        "id": 7931712963,
        "user": "pamela.sena.93"
    },
    {
        "id": 37084966624,
        "user": "livia_marques20"
    },
    {
        "id": 65314969840,
        "user": "pallomaa.m.a"
    },
    {
        "id": 64952248951,
        "user": "paloomamelissa22"
    },
    {
        "id": 66480912827,
        "user": "paola233590"
    },
    {
        "id": 65953006609,
        "user": "franciscaantoniabragac"
    },
    {
        "id": 66125672962,
        "user": "rlk.ninho_022"
    },
    {
        "id": 52015870749,
        "user": "vivi_araujost"
    },
    {
        "id": 286398316,
        "user": "ilanepalacio"
    },
    {
        "id": 65189572688,
        "user": "hnzn.46"
    },
    {
        "id": 44997589111,
        "user": "rlk_gaby028"
    },
    {
        "id": 45268461999,
        "user": "fabrycim_dugrau"
    },
    {
        "id": 55657888957,
        "user": "ana.clara.santiag0"
    },
    {
        "id": 39881622859,
        "user": "_suzaneoficial"
    },
    {
        "id": 37202919817,
        "user": "andressa_freire0903"
    },
    {
        "id": 65658964648,
        "user": "jhoni_o_primo"
    },
    {
        "id": 62380164774,
        "user": "dk_lucazinxs_59d"
    },
    {
        "id": 8700506601,
        "user": "meirevegas"
    },
    {
        "id": 66500914293,
        "user": "lucasfreitas_gk"
    },
    {
        "id": 40199751798,
        "user": "elianepaula148"
    },
    {
        "id": 65880109107,
        "user": "uai.biancabeatriz"
    },
    {
        "id": 64513582298,
        "user": "nascimentoatl2"
    },
    {
        "id": 59197601764,
        "user": "damarisraquel64"
    },
    {
        "id": 65863984702,
        "user": "riquezim_pv7"
    },
    {
        "id": 61028353376,
        "user": "sa4a9_2"
    },
    {
        "id": 65731790621,
        "user": "14biancabeatriz__"
    },
    {
        "id": 56665179256,
        "user": "lorraineesilvaa71"
    },
    {
        "id": 60520819240,
        "user": "riquelme9988_"
    },
    {
        "id": 37387863556,
        "user": "thematheoy_"
    },
    {
        "id": 64060936055,
        "user": "bianca.0614_"
    },
    {
        "id": 40410343564,
        "user": "_rs_rosi7"
    },
    {
        "id": 4093899226,
        "user": "bruniinhagouvea"
    },
    {
        "id": 6780539603,
        "user": "angelagomesalves"
    },
    {
        "id": 35904899788,
        "user": "eliene_edu"
    },
    {
        "id": 3410492042,
        "user": "leicyanearaujo"
    },
    {
        "id": 6651838984,
        "user": "raniely.f"
    },
    {
        "id": 62773069856,
        "user": "3004_inaiee"
    },
    {
        "id": 8534325415,
        "user": "alysonsilvf"
    },
    {
        "id": 48764083057,
        "user": "edineia.cabelos"
    },
    {
        "id": 21848863910,
        "user": "lariieh_ch"
    },
    {
        "id": 1657270513,
        "user": "jainnesantos0706"
    },
    {
        "id": 66523432611,
        "user": "cri_stiane555"
    },
    {
        "id": 65163793099,
        "user": "cristhiane252"
    },
    {
        "id": 63306471056,
        "user": "_dnyelz_7p_77"
    },
    {
        "id": 14730064874,
        "user": "edsonsantos31761"
    },
    {
        "id": 66367435897,
        "user": "vi_vitoria2024almeida"
    },
    {
        "id": 61709503286,
        "user": "ba_bix7"
    },
    {
        "id": 65400460172,
        "user": "vulgo_dl_sc"
    },
    {
        "id": 5399408034,
        "user": "jacyenedasilva"
    },
    {
        "id": 1383743745,
        "user": "valeriiasilva72"
    },
    {
        "id": 33940425838,
        "user": "janainadunga"
    },
    {
        "id": 60382123069,
        "user": "veraluciaalves102"
    },
    {
        "id": 1520187921,
        "user": "laryssamarinho.nutri"
    },
    {
        "id": 51082176108,
        "user": "rapunzeisjuazeiro"
    },
    {
        "id": 1362426180,
        "user": "thaysbeatriz_"
    },
    {
        "id": 13785005310,
        "user": "geniflavia5"
    },
    {
        "id": 6061882534,
        "user": "oliviatallyta"
    },
    {
        "id": 8640926368,
        "user": "giih_ribeiro2303"
    },
    {
        "id": 7956035368,
        "user": "kelly.a.souza"
    },
    {
        "id": 3972167371,
        "user": "vansousa_k"
    },
    {
        "id": 39172976266,
        "user": "santanamaria82"
    },
    {
        "id": 58845279799,
        "user": "ruthevitoria332"
    },
    {
        "id": 3502620450,
        "user": "criislannya"
    },
    {
        "id": 65590583082,
        "user": "eugenia_senna1"
    },
    {
        "id": 64680142589,
        "user": "naiarasilva6538"
    },
    {
        "id": 4041458612,
        "user": "darilenemorais"
    },
    {
        "id": 50218739196,
        "user": "janiele3963"
    },
    {
        "id": 5573882691,
        "user": "irismar_snts"
    },
    {
        "id": 52730996193,
        "user": "francielly__silvah"
    },
    {
        "id": 2228119990,
        "user": "marlucialira795"
    },
    {
        "id": 1900946206,
        "user": "fala_comigobetao"
    },
    {
        "id": 6097924507,
        "user": "jacquelinegoncalves7544"
    },
    {
        "id": 7846717807,
        "user": "gessica_albuquerq"
    },
    {
        "id": 4557761351,
        "user": "wallzinhasillva_h"
    },
    {
        "id": 8788966032,
        "user": "rosileideneudes.vet"
    },
    {
        "id": 1112996952,
        "user": "_rosiane11"
    },
    {
        "id": 52584996093,
        "user": "ksouz_a1"
    },
    {
        "id": 12674845921,
        "user": "ricarte_emilly5"
    },
    {
        "id": 52801023566,
        "user": "manuele_nascimento18"
    },
    {
        "id": 1417894052,
        "user": "andreiaoliiveiraa1"
    },
    {
        "id": 2050163201,
        "user": "moraisvitoria__"
    },
    {
        "id": 59153900183,
        "user": "pattysilvestre30"
    },
    {
        "id": 6978026013,
        "user": "mary21352018"
    },
    {
        "id": 19721261410,
        "user": "dayaneyk____"
    },
    {
        "id": 4044582877,
        "user": "kaianne_sillva"
    },
    {
        "id": 2044443506,
        "user": "estermodas10"
    },
    {
        "id": 6730184085,
        "user": "vieiranunes__"
    },
    {
        "id": 8489745993,
        "user": "vitorialinard_"
    },
    {
        "id": 1537821960,
        "user": "annkatiadaniel"
    },
    {
        "id": 5401787535,
        "user": "taty.arthurr"
    },
    {
        "id": 6450225440,
        "user": "ivone_santooss"
    },
    {
        "id": 65589954072,
        "user": "agencia_____lu"
    },
    {
        "id": 367694256,
        "user": "juliamariiab_"
    },
    {
        "id": 508238784,
        "user": "ju_llyethe"
    },
    {
        "id": 2042310354,
        "user": "antoniapaula.araujo86"
    },
    {
        "id": 8755714785,
        "user": "jan_sampaio_p"
    },
    {
        "id": 66295966706,
        "user": "erlando_forrozeiro_do_brasil"
    },
    {
        "id": 2277922171,
        "user": "fabiol.lima"
    },
    {
        "id": 51919484896,
        "user": "_laryssa.goncalves"
    },
    {
        "id": 62770770288,
        "user": "sarinha_v14"
    },
    {
        "id": 61850446143,
        "user": "_cla.vier"
    },
    {
        "id": 10658531673,
        "user": "ellensarah___"
    },
    {
        "id": 1929406237,
        "user": "larissaa_sg"
    },
    {
        "id": 8063263497,
        "user": "_kamilasous"
    },
    {
        "id": 5879681801,
        "user": "joaootaviocaldas1"
    },
    {
        "id": 65875555669,
        "user": "solfitnesmodas"
    },
    {
        "id": 10157552523,
        "user": "adv.batistajr"
    },
    {
        "id": 1420459133,
        "user": "leoo.silva36"
    },
    {
        "id": 298370149,
        "user": "wesleygaldino"
    },
    {
        "id": 2288943051,
        "user": "gledsonmaiaa"
    },
    {
        "id": 38331964386,
        "user": "feliiipe_alvess"
    },
    {
        "id": 1576307744,
        "user": "emanuelbbsouza"
    },
    {
        "id": 567880544,
        "user": "regianebandeira"
    },
    {
        "id": 1470690863,
        "user": "ramizielly"
    },
    {
        "id": 4070266924,
        "user": "p.e01"
    },
    {
        "id": 663857502,
        "user": "italomariinho"
    },
    {
        "id": 13692194319,
        "user": "essemanoel"
    },
    {
        "id": 347758003,
        "user": "sarathayna"
    },
    {
        "id": 4319274391,
        "user": "inayarasouzateixeira"
    },
    {
        "id": 46534804350,
        "user": "movlarof"
    },
    {
        "id": 584991094,
        "user": "ericb_maria"
    },
    {
        "id": 7772146281,
        "user": "juniiormoral10"
    },
    {
        "id": 35929321723,
        "user": "naceliane_raphael"
    },
    {
        "id": 32348158430,
        "user": "cassia_cicera_77"
    },
    {
        "id": 1735373803,
        "user": "yuri_almeida___"
    },
    {
        "id": 32718677458,
        "user": "sabryna___123_4"
    },
    {
        "id": 6236383362,
        "user": "drpedroamoraes"
    },
    {
        "id": 9280477151,
        "user": "nathalyarodrigovitoriano"
    },
    {
        "id": 646852277,
        "user": "diogo.soarees"
    },
    {
        "id": 5383757476,
        "user": "david_ferreiira24"
    },
    {
        "id": 228706557,
        "user": "sbianca"
    },
    {
        "id": 61802450630,
        "user": "inovar_projetar"
    },
    {
        "id": 3115002083,
        "user": "josy_limma29"
    },
    {
        "id": 3543664681,
        "user": "vitordedier"
    },
    {
        "id": 263776069,
        "user": "anny_uaai"
    },
    {
        "id": 65641798876,
        "user": "moda_fitness_araripina"
    },
    {
        "id": 5609286177,
        "user": "cleitonn_personal"
    },
    {
        "id": 5578714375,
        "user": "_regivaniasoares"
    },
    {
        "id": 2564014539,
        "user": "karol_loreto_"
    },
    {
        "id": 6060871869,
        "user": "mirellysanttos__"
    },
    {
        "id": 279155125,
        "user": "thiagonascimentomedvet"
    },
    {
        "id": 51496436512,
        "user": "_________yan_amaro"
    },
    {
        "id": 25524394798,
        "user": "i.siilva_05"
    },
    {
        "id": 1676018948,
        "user": "christianoaguiar_"
    },
    {
        "id": 1021048369,
        "user": "eduardaasoares__"
    },
    {
        "id": 2078082407,
        "user": "elisson_neriss"
    },
    {
        "id": 273513865,
        "user": "mallu_araujo"
    },
    {
        "id": 6592305677,
        "user": "joaogadelha_55"
    },
    {
        "id": 4158187491,
        "user": "edilmarleite"
    },
    {
        "id": 11696172015,
        "user": "laniasouza3068"
    },
    {
        "id": 48664093956,
        "user": "dra.dannielly_estetica"
    },
    {
        "id": 10155588546,
        "user": "rayaane_santoss88888"
    },
    {
        "id": 1021196196,
        "user": "mauriliobarbosa.enf"
    },
    {
        "id": 27157752448,
        "user": "samara_santos_souza__"
    },
    {
        "id": 58460143094,
        "user": "sillva2911"
    },
    {
        "id": 51766203809,
        "user": "_darlene.er"
    },
    {
        "id": 2533094860,
        "user": "espacovi.p"
    },
    {
        "id": 46936356626,
        "user": "negamalucavelas"
    },
    {
        "id": 2107873502,
        "user": "ei_luh.silva"
    },
    {
        "id": 14281475989,
        "user": "8197karina"
    },
    {
        "id": 51169711642,
        "user": "iraneide2022"
    },
    {
        "id": 21993582007,
        "user": "vitoriiayasmin662"
    },
    {
        "id": 9184179477,
        "user": "rosana66142"
    },
    {
        "id": 17875705669,
        "user": "anacarolina.carol.1466"
    },
    {
        "id": 30853078328,
        "user": "maary_2021"
    },
    {
        "id": 8069910372,
        "user": "silvanaramos3"
    },
    {
        "id": 6160542703,
        "user": "janainasilvamatias"
    },
    {
        "id": 38518475116,
        "user": "macedoaldecir"
    },
    {
        "id": 64426782206,
        "user": "alicemaille__"
    },
    {
        "id": 3675656384,
        "user": "joanarodrigues3456"
    },
    {
        "id": 3248700847,
        "user": "lenynha7315"
    },
    {
        "id": 6582691145,
        "user": "barbara_0_0_"
    },
    {
        "id": 6006560332,
        "user": "tluiza.b"
    },
    {
        "id": 1485986023,
        "user": "jannyoliveira65"
    },
    {
        "id": 1469850779,
        "user": "luana222324"
    },
    {
        "id": 47149355018,
        "user": "enmilly1278"
    },
    {
        "id": 2918692555,
        "user": "danilo_mascarenhas16"
    },
    {
        "id": 30324597928,
        "user": "_miryammikelly"
    },
    {
        "id": 37031393873,
        "user": "viviane.rodrigues_2"
    },
    {
        "id": 13209943095,
        "user": "gesilania3"
    },
    {
        "id": 57863587130,
        "user": "_simoonee31"
    },
    {
        "id": 2041493938,
        "user": "herriclles"
    },
    {
        "id": 47711153087,
        "user": "frlirenepb"
    },
    {
        "id": 480460320,
        "user": "_deborahpinheiro"
    },
    {
        "id": 1302062106,
        "user": "gerlaniaregina"
    },
    {
        "id": 18650278795,
        "user": "edivaniaviana14"
    },
    {
        "id": 351050689,
        "user": "guedimfeitosa"
    },
    {
        "id": 1284875881,
        "user": "camilaa_ml"
    },
    {
        "id": 53868325828,
        "user": "danny_silva2010"
    },
    {
        "id": 26174040920,
        "user": "mateusviannaof"
    },
    {
        "id": 2140588458,
        "user": "ercules_miguel"
    },
    {
        "id": 33223927201,
        "user": "laaryssa__felipeh"
    },
    {
        "id": 1094016805,
        "user": "taylanesilvamakeup"
    },
    {
        "id": 1707365817,
        "user": "stelinard"
    },
    {
        "id": 47407008979,
        "user": "josivania.santos123"
    },
    {
        "id": 65672276629,
        "user": "treinoscorrida"
    },
    {
        "id": 65472409284,
        "user": "assessorialaisa"
    },
    {
        "id": 15146133271,
        "user": "s4vio.ofc"
    },
    {
        "id": 7784500213,
        "user": "kaleb_pereiraa"
    },
    {
        "id": 4010925508,
        "user": "mesquita.2018"
    },
    {
        "id": 4765477326,
        "user": "damariss_dias"
    },
    {
        "id": 8350421131,
        "user": "paulo.pjoliveira"
    },
    {
        "id": 1340849364,
        "user": "cearapriscilasa"
    },
    {
        "id": 16954358846,
        "user": "andradelaisa_"
    },
    {
        "id": 254770508,
        "user": "eriikanogueira_"
    },
    {
        "id": 6825160722,
        "user": "_vivi_53"
    },
    {
        "id": 7636867908,
        "user": "iria.caroline"
    },
    {
        "id": 39230508072,
        "user": "dona_mina_"
    },
    {
        "id": 50371815072,
        "user": "suzyfreitas120"
    },
    {
        "id": 33845252936,
        "user": "andreiaa_damascenoo"
    },
    {
        "id": 500497380,
        "user": "andressalorena4"
    },
    {
        "id": 775418864,
        "user": "mateusamp__"
    },
    {
        "id": 6937000698,
        "user": "mclarasouzas"
    },
    {
        "id": 62166247071,
        "user": "willamyfreitas37"
    },
    {
        "id": 46229286171,
        "user": "bella.chicconceito"
    },
    {
        "id": 15212144453,
        "user": "everglow_2004"
    },
    {
        "id": 17672815556,
        "user": "thelmaavalenthina"
    },
    {
        "id": 58922519362,
        "user": "edinacarla.16"
    },
    {
        "id": 57810637714,
        "user": "nageladayanne"
    },
    {
        "id": 14644592249,
        "user": "marianatalia517"
    },
    {
        "id": 62030186328,
        "user": "amandagualberto2024"
    },
    {
        "id": 55238331540,
        "user": "rabelojonas6"
    },
    {
        "id": 4167997208,
        "user": "marinasampaio72"
    },
    {
        "id": 2137616998,
        "user": "camila_rodrigues2000"
    },
    {
        "id": 2067952661,
        "user": "ramoscorrinha4"
    },
    {
        "id": 1589110114,
        "user": "fernandaalaza"
    },
    {
        "id": 7565971380,
        "user": "leidyane_liima"
    },
    {
        "id": 6201236166,
        "user": "thauwanne"
    },
    {
        "id": 6627878641,
        "user": "_.gabyyss.__"
    },
    {
        "id": 539291126,
        "user": "yas18barbosa"
    },
    {
        "id": 6364508307,
        "user": "lc_bronze"
    },
    {
        "id": 63524626248,
        "user": "_myllasampaio"
    },
    {
        "id": 1553224757,
        "user": "cidinha87"
    },
    {
        "id": 476358462,
        "user": "marianatalialeitedantas"
    },
    {
        "id": 1660661049,
        "user": "samu_a7x"
    },
    {
        "id": 1493123378,
        "user": "hedna_santos"
    },
    {
        "id": 4053846688,
        "user": "alyandresilva"
    },
    {
        "id": 7042656466,
        "user": "maraguilherme_1"
    },
    {
        "id": 64204924627,
        "user": "thai_allcantara"
    },
    {
        "id": 8258286809,
        "user": "rayani_alves1"
    },
    {
        "id": 5987719306,
        "user": "joao.paulo_1914"
    },
    {
        "id": 1413207201,
        "user": "katiaerummenigge"
    },
    {
        "id": 28644082418,
        "user": "liz.lizandrah"
    },
    {
        "id": 53593432553,
        "user": "llucas_santoss0y"
    },
    {
        "id": 25480965429,
        "user": "taynewermeson"
    },
    {
        "id": 2254939208,
        "user": "edinalva_cruz13"
    },
    {
        "id": 265559540,
        "user": "personalcalixto"
    },
    {
        "id": 18613415770,
        "user": "anacristinasouza_araujo"
    },
    {
        "id": 1725152435,
        "user": "amandalende"
    },
    {
        "id": 39722732993,
        "user": "thayssantosof"
    },
    {
        "id": 8688872544,
        "user": "ginasousa2806"
    },
    {
        "id": 1124690408,
        "user": "gabrielfranklim0_"
    },
    {
        "id": 4490809413,
        "user": "luanna.mendonca"
    },
    {
        "id": 7078547890,
        "user": "_lessabrgs_"
    },
    {
        "id": 49036150227,
        "user": "livia.svno"
    },
    {
        "id": 53530684525,
        "user": "douglascastelo129"
    },
    {
        "id": 5940866648,
        "user": "nicollypont"
    },
    {
        "id": 57689725958,
        "user": "mahhdias___"
    },
    {
        "id": 3037002333,
        "user": "gilsonsobreira"
    },
    {
        "id": 21379964867,
        "user": "gutemberguesouza"
    },
    {
        "id": 3869807091,
        "user": "kaylane_gon"
    },
    {
        "id": 3041659757,
        "user": "michelle.sayonara"
    },
    {
        "id": 52301221466,
        "user": "marimaristn"
    },
    {
        "id": 9012565263,
        "user": "mariahelena.100"
    },
    {
        "id": 9241641044,
        "user": "lluanadantas_"
    },
    {
        "id": 27227902586,
        "user": "agenciacoffeon"
    },
    {
        "id": 28910956261,
        "user": "luanafenelonde"
    }
]